wapiti_arsenic/__init__.py
wapiti_arsenic/actions.py
wapiti_arsenic/browsers.py
wapiti_arsenic/connection.py
wapiti_arsenic/constants.py
wapiti_arsenic/errors.py
wapiti_arsenic/helpers.py
wapiti_arsenic/http.py
wapiti_arsenic/keys.py
wapiti_arsenic/services.py
wapiti_arsenic/session.py
wapiti_arsenic/subprocess.py
wapiti_arsenic/utils.py
wapiti_arsenic/webdriver.py
wapiti_arsenic-28.4.dist-info/LICENSE
wapiti_arsenic-28.4.dist-info/METADATA
wapiti_arsenic-28.4.dist-info/WHEEL
wapiti_arsenic-28.4.dist-info/entry_points.txt
wapiti_arsenic-28.4.dist-info/RECORD
