Metadata-Version: 2.1
Name: wapiti-arsenic
Version: 28.4
Summary: Asynchronous WebDriver client
Home-page: https://github.com/wapiti-scanner/arsenic/
License: Apache-2.0
Keywords: asyncio
Author: Jonas Obrist
Author-email: jonas.obrist@hennge.com
Requires-Python: >=3.10,<3.14
Classifier: Development Status :: 5 - Production/Stable
Classifier: Framework :: AsyncIO
Classifier: License :: OSI Approved :: Apache Software License
Classifier: Operating System :: MacOS :: MacOS X
Classifier: Operating System :: Microsoft :: Windows
Classifier: Operating System :: POSIX :: Linux
Classifier: Programming Language :: Python :: 3
Classifier: Programming Language :: Python :: 3.10
Classifier: Programming Language :: Python :: 3.11
Classifier: Programming Language :: Python :: 3 :: Only
Classifier: Programming Language :: Python :: 3.10
Classifier: Programming Language :: Python :: 3.11
Classifier: Programming Language :: Python :: 3.12
Classifier: Programming Language :: Python :: 3.13
Classifier: Topic :: Software Development :: Testing
Requires-Dist: attrs (>=23.2,<24.3)
Requires-Dist: httpx (>=0.27,<1.0)
Requires-Dist: packaging (>=23.0,<26.0)
Requires-Dist: structlog (>=23.1,<25.0)
Project-URL: Documentation, https://arsenic.readthedocs.io/en/latest/
Project-URL: Repository, https://github.com/wapiti-scanner/arsenic/
